typedconfig/__init__.py
typedconfig/__version__.py
typedconfig/casts.py
typedconfig/config.py
typedconfig/provider.py
typedconfig/py.typed
typedconfig/source.py
typed_config-2.0.3.dist-info/LICENSE
typed_config-2.0.3.dist-info/METADATA
typed_config-2.0.3.dist-info/WHEEL
typed_config-2.0.3.dist-info/top_level.txt
typed_config-2.0.3.dist-info/RECORD
