Metadata-Version: 2.1
Name: typed-config
Version: 2.0.3
Summary: Typed, extensible, dependency free configuration reader for Python projects for multiple config sources and working well in IDEs for great autocomplete performance.
Home-page: https://github.com/bwindsor/typed-config
Author: Ben Windsor
Author-email: 
License: MIT
Classifier: Programming Language :: Python :: 3
Classifier: Programming Language :: Python :: 3.8
Classifier: Programming Language :: Python :: 3.9
Classifier: Programming Language :: Python :: 3.10
Classifier: Programming Language :: Python :: 3.11
Classifier: Programming Language :: Python :: 3.12
Classifier: Development Status :: 4 - Beta
Classifier: Intended Audience :: Developers
Classifier: License :: OSI Approved :: MIT License
Classifier: Topic :: Software Development
Classifier: Typing :: Typed
Requires-Python: >=3.6.0
License-File: LICENSE
